pdr_utils/__init__.py
pdr_utils/contract.py
pdr_utils/subgraph.py
pdr_utils-0.0.14.dist-info/LICENSE
pdr_utils-0.0.14.dist-info/METADATA
pdr_utils-0.0.14.dist-info/WHEEL
pdr_utils-0.0.14.dist-info/top_level.txt
pdr_utils-0.0.14.dist-info/RECORD
