Metadata-Version: 2.1
Name: pdr-utils
Version: 0.0.14
Summary: Predictoor utils lib.
Home-page: https://github.com/oceanprotocol/pdr-utils
Author: oceanprotocol
Author-email: devops@oceanprotocol.com
License: Apache Software License 2.0
Classifier: Development Status :: 2 - Pre-Alpha
Classifier: Intended Audience :: Developers
Classifier: License :: OSI Approved :: Apache Software License
Classifier: Natural Language :: English
Classifier: Programming Language :: Python :: 3.8
License-File: LICENSE
Requires-Dist: enforce-typing
Requires-Dist: pylint
Requires-Dist: bumpversion
Requires-Dist: requests
Requires-Dist: web3
Requires-Dist: coverage
Requires-Dist: eth-account
Requires-Dist: pathlib
Requires-Dist: eth-keys
Requires-Dist: ocean-contracts (==2.0.0a2)
